FlintCLN/FlintCLN.py
FlintCLN/__init__.py
FlintCLN/cmd.py
FlintCLN/tests/__init__.py
FlintCLN/tests/test_FlintCLN.py
FlintCLN-0.1.0a0.dist-info/LICENSE.txt
FlintCLN-0.1.0a0.dist-info/METADATA
FlintCLN-0.1.0a0.dist-info/WHEEL
FlintCLN-0.1.0a0.dist-info/entry_points.txt
FlintCLN-0.1.0a0.dist-info/top_level.txt
FlintCLN-0.1.0a0.dist-info/RECORD
