Metadata-Version: 2.1
Name: FlintCLN
Version: 0.1.0a0
Summary: Flint is a linting tool to ensure projects in the Ficklin Research Program follow expected standards.
Home-page: https://gitlab.com/ficklin-lab/flintcln
Author: Ficklin
License: GNU General Public License v3.0
Platform: UNKNOWN
Requires-Python: >=3.6
License-File: LICENSE.txt
